Workbook
Name Slicer_Cost_Category: #N/A
Name Slicer_Project_Name1: #N/A

Sheet Projects
A1: Project ID | B1: Project Name | C1: Client ID | D1: Project Manager | E1: Region | F1: Contract Value | G1: Start Date | H1: End Date | I1: Status | J1: Client Name
A2: P001 | B2: Bridge Alpha | C2: C001 | D2: James Carter | E2: Midlands | F2: 5200000 | G2: 46023 | H2: 46326 | I2: Active | J2: =_xll.XLOOKUP(tblProjects[[#This Row],[Client ID]],tblClients[Client ID],tblClients[Client Name],"Not Found") -> Network Rail
A3: P002 | B3: Water Main Bravo | C3: C002 | D3: Sarah Ahmed | E3: South East | F3: 3800000 | G3: 46068 | H3: 46371 | I3: Active | J3: =_xll.XLOOKUP(tblProjects[[#This Row],[Client ID]],tblClients[Client ID],tblClients[Client Name],"Not Found") -> Thames Water
A4: P003 | B4: Highway Charlie | C4: C003 | D4: Michael Green | E4: North West | F4: 6100000 | G4: 46082 | H4: 46418 | I4: Active | J4: =_xll.XLOOKUP(tblProjects[[#This Row],[Client ID]],tblClients[Client ID],tblClients[Client Name],"Not Found") -> National Highways
A5: P004 | B5: Rail Extension Delta | C5: C001 | D5: Emma Lewis | E5: Midlands | F5: 4700000 | G5: 46127 | H5: 46477 | I5: Active | J5: =_xll.XLOOKUP(tblProjects[[#This Row],[Client ID]],tblClients[Client ID],tblClients[Client Name],"Not Found") -> Network Rail
A6: P005 | B6: Flood Defence Echo | C6: C004 | D6: Daniel Hughes | E6: South West | F6: 2950000 | G6: 46143 | H6: 46356 | I6: Planning | J6: =_xll.XLOOKUP(tblProjects[[#This Row],[Client ID]],tblClients[Client ID],tblClients[Client Name],"Not Found") -> Environment Agency
F7: =SUBTOTAL(109,tblProjects[Contract Value]) -> 22750000

Sheet Clients
A1: Client ID | B1: Client Name | C1: Contact Person | D1: Email | E1: Phone
A2: C001 | B2: Network Rail | C2: David Smith | D2: david.smith@networkrail.co.uk | E2: 020 7946 1001
A3: C002 | B3: Thames Water | C3: Emily Jones | D3: emily.jones@thameswater.co.uk | E3: 020 7946 1002
A4: C003 | B4: National Highways | C4: Peter Brown | D4: peter.brown@nationalhighways.co.uk | E4: 020 7946 1003
A5: C004 | B5: Environment Agency | C5: Lisa Taylor | D5: lisa.taylor@environment-agency.gov.uk | E5: 020 7946 1004

Sheet Budget
A1: Project ID | B1: Category ID | C1: Budget Amount | D1: Cost Category
A2: P001 | B2: CAT01 | C2: 1170000 | D2: =_xll.XLOOKUP(tblBudget[[#This Row],[Category ID]],tblCostCategories[Category ID],tblCostCategories[Cost Category],"Category not found") -> Labour
A3: P001 | B3: CAT02 | C3: 1498000 | D3: =_xll.XLOOKUP(tblBudget[[#This Row],[Category ID]],tblCostCategories[Category ID],tblCostCategories[Cost Category],"Category not found") -> Materials
A4: P001 | B4: CAT03 | C4: 608000 | D4: =_xll.XLOOKUP(tblBudget[[#This Row],[Category ID]],tblCostCategories[Category ID],tblCostCategories[Cost Category],"Category not found") -> Plant Hire
A5: P001 | B5: CAT04 | C5: 796000 | D5: =_xll.XLOOKUP(tblBudget[[#This Row],[Category ID]],tblCostCategories[Category ID],tblCostCategories[Cost Category],"Category not found") -> Subcontractors
A6: P001 | B6: CAT05 | C6: 187000 | D6: =_xll.XLOOKUP(tblBudget[[#This Row],[Category ID]],tblCostCategories[Category ID],tblCostCategories[Cost Category],"Category not found") -> Fuel & Transport
A7: P001 | B7: CAT06 | C7: 281000 | D7: =_xll.XLOOKUP(tblBudget[[#This Row],[Category ID]],tblCostCategories[Category ID],tblCostCategories[Cost Category],"Category not found") -> Site Overheads
A8: P001 | B8: CAT07 | C8: 140000 | D8: =_xll.XLOOKUP(tblBudget[[#This Row],[Category ID]],tblCostCategories[Category ID],tblCostCategories[Cost Category],"Category not found") -> Contingency
A9: P002 | B9: CAT01 | C9: 958000 | D9: =_xll.XLOOKUP(tblBudget[[#This Row],[Category ID]],tblCostCategories[Category ID],tblCostCategories[Cost Category],"Category not found") -> Labour
A10: P002 | B10: CAT02 | C10: 923000 | D10: =_xll.XLOOKUP(tblBudget[[#This Row],[Category ID]],tblCostCategories[Category ID],tblCostCategories[Cost Category],"Category not found") -> Materials
A11: P002 | B11: CAT03 | C11: 513000 | D11: =_xll.XLOOKUP(tblBudget[[#This Row],[Category ID]],tblCostCategories[Category ID],tblCostCategories[Cost Category],"Category not found") -> Plant Hire
A12: P002 | B12: CAT04 | C12: 547000 | D12: =_xll.XLOOKUP(tblBudget[[#This Row],[Category ID]],tblCostCategories[Category ID],tblCostCategories[Cost Category],"Category not found") -> Subcontractors
A13: P002 | B13: CAT05 | C13: 171000 | D13: =_xll.XLOOKUP(tblBudget[[#This Row],[Category ID]],tblCostCategories[Category ID],tblCostCategories[Cost Category],"Category not found") -> Fuel & Transport
... A36: P005 | B36: CAT07 | C36: 79000 | D36: =_xll.XLOOKUP(tblBudget[[#This Row],[Category ID]],tblCostCategories[Category ID],tblCostCategories[Cost Category],"Category not found") -> Contingency

Sheet Cost_Categories
A1: Category ID | B1: Cost Category
A2: CAT01 | B2: Labour
A3: CAT02 | B3: Materials
A4: CAT03 | B4: Plant Hire
A5: CAT04 | B5: Subcontractors
A6: CAT05 | B6: Fuel & Transport
A7: CAT06 | B7: Site Overheads
A8: CAT07 | B8: Contingency

Sheet Actual_Cost
A1: cat | B1: Invoice No | C1: Project ID | D1: Project Name | E1: Category ID | F1: Cost Category | G1: Supplier | H1: Description | I1: Amount | J1: Month
A2: 46030 | B2: INV-1001 | C2: P001 | D2: =_xll.XLOOKUP(tblActualCosts[[#This Row],[Project ID]],tblProjects[Project ID],tblProjects[Project Name],"Project Not Found") -> Bridge Alpha | E2: CAT02 | F2: =_xll.XLOOKUP(tblActualCosts[[#This Row],[Category ID]],tblCostCategories[Category ID],tblCostCategories[Cost Category],"category Not Found") -> Materials | G2: Midland Steel Ltd | H2: Reinforcement steel | I2: 185000 | J2: =EOMONTH(tblActualCosts[[#This Row],[cat]],-1)+1 -> 46023
A3: 46037 | B3: INV-1002 | C3: P001 | D3: =_xll.XLOOKUP(tblActualCosts[[#This Row],[Project ID]],tblProjects[Project ID],tblProjects[Project Name],"Project Not Found") -> Bridge Alpha | E3: CAT01 | F3: =_xll.XLOOKUP(tblActualCosts[[#This Row],[Category ID]],tblCostCategories[Category ID],tblCostCategories[Cost Category],"category Not Found") -> Labour | G3: BuildForce Labour | H3: January site labour | I3: 98000 | J3: =EOMONTH(tblActualCosts[[#This Row],[cat]],-1)+1 -> 46023
A4: 46044 | B4: INV-1003 | C4: P001 | D4: =_xll.XLOOKUP(tblActualCosts[[#This Row],[Project ID]],tblProjects[Project ID],tblProjects[Project Name],"Project Not Found") -> Bridge Alpha | E4: CAT03 | F4: =_xll.XLOOKUP(tblActualCosts[[#This Row],[Category ID]],tblCostCategories[Category ID],tblCostCategories[Cost Category],"category Not Found") -> Plant Hire | G4: Heavy Plant Hire Ltd | H4: Excavator hire | I4: 46000 | J4: =EOMONTH(tblActualCosts[[#This Row],[cat]],-1)+1 -> 46023
A5: 46058 | B5: INV-1004 | C5: P001 | D5: =_xll.XLOOKUP(tblActualCosts[[#This Row],[Project ID]],tblProjects[Project ID],tblProjects[Project Name],"Project Not Found") -> Bridge Alpha | E5: CAT02 | F5: =_xll.XLOOKUP(tblActualCosts[[#This Row],[Category ID]],tblCostCategories[Category ID],tblCostCategories[Cost Category],"category Not Found") -> Materials | G5: Concrete Solutions | H5: Structural concrete | I5: 142000 | J5: =EOMONTH(tblActualCosts[[#This Row],[cat]],-1)+1 -> 46054
A6: 46071 | B6: INV-1005 | C6: P001 | D6: =_xll.XLOOKUP(tblActualCosts[[#This Row],[Project ID]],tblProjects[Project ID],tblProjects[Project Name],"Project Not Found") -> Bridge Alpha | E6: CAT04 | F6: =_xll.XLOOKUP(tblActualCosts[[#This Row],[Category ID]],tblCostCategories[Category ID],tblCostCategories[Cost Category],"category Not Found") -> Subcontractors | G6: Apex Structures | H6: Specialist steel installation | I6: 125000 | J6: =EOMONTH(tblActualCosts[[#This Row],[cat]],-1)+1 -> 46054
A7: 46091 | B7: INV-1006 | C7: P001 | D7: =_xll.XLOOKUP(tblActualCosts[[#This Row],[Project ID]],tblProjects[Project ID],tblProjects[Project Name],"Project Not Found") -> Bridge Alpha | E7: CAT01 | F7: =_xll.XLOOKUP(tblActualCosts[[#This Row],[Category ID]],tblCostCategories[Category ID],tblCostCategories[Cost Category],"category Not Found") -> Labour | G7: BuildForce Labour | H7: February and March labour | I7: 185000 | J7: =EOMONTH(tblActualCosts[[#This Row],[cat]],-1)+1 -> 46082
A8: 46098 | B8: INV-1007 | C8: P001 | D8: =_xll.XLOOKUP(tblActualCosts[[#This Row],[Project ID]],tblProjects[Project ID],tblProjects[Project Name],"Project Not Found") -> Bridge Alpha | E8: CAT05 | F8: =_xll.XLOOKUP(tblActualCosts[[#This Row],[Category ID]],tblCostCategories[Category ID],tblCostCategories[Cost Category],"category Not Found") -> Fuel & Transport | G8: UK Fuel Services | H8: Diesel and transport | I8: 32000 | J8: =EOMONTH(tblActualCosts[[#This Row],[cat]],-1)+1 -> 46082
A9: 46116 | B9: INV-1008 | C9: P001 | D9: =_xll.XLOOKUP(tblActualCosts[[#This Row],[Project ID]],tblProjects[Project ID],tblProjects[Project Name],"Project Not Found") -> Bridge Alpha | E9: CAT06 | F9: =_xll.XLOOKUP(tblActualCosts[[#This Row],[Category ID]],tblCostCategories[Category ID],tblCostCategories[Cost Category],"category Not Found") -> Site Overheads | G9: SiteSafe Services | H9: Site accommodation and security | I9: 48000 | J9: =EOMONTH(tblActualCosts[[#This Row],[cat]],-1)+1 -> 46113
A10: 46074 | B10: INV-2001 | C10: P002 | D10: =_xll.XLOOKUP(tblActualCosts[[#This Row],[Project ID]],tblProjects[Project ID],tblProjects[Project Name],"Project Not Found") -> Water Main Bravo | E10: CAT01 | F10: =_xll.XLOOKUP(tblActualCosts[[#This Row],[Category ID]],tblCostCategories[Category ID],tblCostCategories[Cost Category],"category Not Found") -> Labour | G10: Aqua Civil Labour | H10: Initial site labour | I10: 76000 | J10: =EOMONTH(tblActualCosts[[#This Row],[cat]],-1)+1 -> 46054
A11: 46081 | B11: INV-2002 | C11: P002 | D11: =_xll.XLOOKUP(tblActualCosts[[#This Row],[Project ID]],tblProjects[Project ID],tblProjects[Project Name],"Project Not Found") -> Water Main Bravo | E11: CAT03 | F11: =_xll.XLOOKUP(tblActualCosts[[#This Row],[Category ID]],tblCostCategories[Category ID],tblCostCategories[Cost Category],"category Not Found") -> Plant Hire | G11: Excavation Plant UK | H11: Trenching equipment | I11: 68000 | J11: =EOMONTH(tblActualCosts[[#This Row],[cat]],-1)+1 -> 46054
A12: 46093 | B12: INV-2003 | C12: P002 | D12: =_xll.XLOOKUP(tblActualCosts[[#This Row],[Project ID]],tblProjects[Project ID],tblProjects[Project Name],"Project Not Found") -> Water Main Bravo | E12: CAT02 | F12: =_xll.XLOOKUP(tblActualCosts[[#This Row],[Category ID]],tblCostCategories[Category ID],tblCostCategories[Cost Category],"category Not Found") -> Materials | G12: PipeWorks UK | H12: Water pipes | I12: 154000 | J12: =EOMONTH(tblActualCosts[[#This Row],[cat]],-1)+1 -> 46082
A13: 46106 | B13: INV-2004 | C13: P002 | D13: =_xll.XLOOKUP(tblActualCosts[[#This Row],[Project ID]],tblProjects[Project ID],tblProjects[Project Name],"Project Not Found") -> Water Main Bravo | E13: CAT04 | F13: =_xll.XLOOKUP(tblActualCosts[[#This Row],[Category ID]],tblCostCategories[Category ID],tblCostCategories[Cost Category],"category Not Found") -> Subcontractors | G13: Utility Specialists Ltd | H13: Specialist installation work | I13: 92000 | J13: =EOMONTH(tblActualCosts[[#This Row],[cat]],-1)+1 -> 46082
... A29: 46172 | B29: INV-5004 | C29: P005 | D29: =_xll.XLOOKUP(tblActualCosts[[#This Row],[Project ID]],tblProjects[Project ID],tblProjects[Project Name],"Project Not Found") -> Flood Defence Echo | E29: CAT02 | F29: =_xll.XLOOKUP(tblActualCosts[[#This Row],[Category ID]],tblCostCategories[Category ID],tblCostCategories[Cost Category],"category Not Found") -> Materials | G29: Barrier Systems UK | H29: Flood barrier materials | I29: 121000 | J29: =EOMONTH(tblActualCosts[[#This Row],[cat]],-1)+1 -> 46143

Sheet Cost_Reconciliation
A1: Project ID | B1: Project Name | C1: Contract Value | D1: Cost Budget | E1: Planned Margin | F1: Margin % | G1: Actual Spend | H1: Remaining Budget | I1: Budget Used %
A2: P001 | B2: =_xll.XLOOKUP(tblReconciliation[[#This Row],[Project ID]],tblProjects[Project ID],tblProjects[Project Name],"Project Not Found") -> Bridge Alpha | C2: =_xll.XLOOKUP(tblReconciliation[[#This Row],[Project ID]],tblProjects[Project ID],tblProjects[Contract Value],"Budget Not Found") -> 5200000 | D2: =SUMIFS(tblBudget[Budget Amount],tblBudget[Project ID],tblReconciliation[[#This Row],[Project ID]]) -> 4680000 | E2: =tblReconciliation[[#This Row],[Contract Value]]-tblReconciliation[[#This Row],[Cost Budget]] -> 520000 | F2: =IFERROR(tblReconciliation[[#This Row],[Planned Margin]]/tblReconciliation[[#This Row],[Contract Value]],0) -> 0.1 | G2: =SUMIFS(tblActualCosts[Amount],tblActualCosts[Project ID],tblReconciliation[Project ID]) -> 861000 | H2: =tblReconciliation[[#This Row],[Cost Budget]]-tblReconciliation[[#This Row],[Actual Spend]] -> 3819000 | I2: =IFERROR(tblReconciliation[[#This Row],[Actual Spend]]/tblReconciliation[[#This Row],[Cost Budget]],0) -> 0.18397436
A3: P002 | B3: =_xll.XLOOKUP(tblReconciliation[[#This Row],[Project ID]],tblProjects[Project ID],tblProjects[Project Name],"Project Not Found") -> Water Main Bravo | C3: =_xll.XLOOKUP(tblReconciliation[[#This Row],[Project ID]],tblProjects[Project ID],tblProjects[Contract Value],"Budget Not Found") -> 3800000 | D3: =SUMIFS(tblBudget[Budget Amount],tblBudget[Project ID],tblReconciliation[[#This Row],[Project ID]]) -> 3420000 | E3: =tblReconciliation[[#This Row],[Contract Value]]-tblReconciliation[[#This Row],[Cost Budget]] -> 380000 | F3: =IFERROR(tblReconciliation[[#This Row],[Planned Margin]]/tblReconciliation[[#This Row],[Contract Value]],0) -> 0.1 | G3: =SUMIFS(tblActualCosts[Amount],tblActualCosts[Project ID],tblReconciliation[Project ID]) -> 504000 | H3: =tblReconciliation[[#This Row],[Cost Budget]]-tblReconciliation[[#This Row],[Actual Spend]] -> 2916000 | I3: =IFERROR(tblReconciliation[[#This Row],[Actual Spend]]/tblReconciliation[[#This Row],[Cost Budget]],0) -> 0.14736842
A4: P003 | B4: =_xll.XLOOKUP(tblReconciliation[[#This Row],[Project ID]],tblProjects[Project ID],tblProjects[Project Name],"Project Not Found") -> Highway Charlie | C4: =_xll.XLOOKUP(tblReconciliation[[#This Row],[Project ID]],tblProjects[Project ID],tblProjects[Contract Value],"Budget Not Found") -> 6100000 | D4: =SUMIFS(tblBudget[Budget Amount],tblBudget[Project ID],tblReconciliation[[#This Row],[Project ID]]) -> 5490000 | E4: =tblReconciliation[[#This Row],[Contract Value]]-tblReconciliation[[#This Row],[Cost Budget]] -> 610000 | F4: =IFERROR(tblReconciliation[[#This Row],[Planned Margin]]/tblReconciliation[[#This Row],[Contract Value]],0) -> 0.1 | G4: =SUMIFS(tblActualCosts[Amount],tblActualCosts[Project ID],tblReconciliation[Project ID]) -> 877000 | H4: =tblReconciliation[[#This Row],[Cost Budget]]-tblReconciliation[[#This Row],[Actual Spend]] -> 4613000 | I4: =IFERROR(tblReconciliation[[#This Row],[Actual Spend]]/tblReconciliation[[#This Row],[Cost Budget]],0) -> 0.15974499
A5: P004 | B5: =_xll.XLOOKUP(tblReconciliation[[#This Row],[Project ID]],tblProjects[Project ID],tblProjects[Project Name],"Project Not Found") -> Rail Extension Delta | C5: =_xll.XLOOKUP(tblReconciliation[[#This Row],[Project ID]],tblProjects[Project ID],tblProjects[Contract Value],"Budget Not Found") -> 4700000 | D5: =SUMIFS(tblBudget[Budget Amount],tblBudget[Project ID],tblReconciliation[[#This Row],[Project ID]]) -> 4230000 | E5: =tblReconciliation[[#This Row],[Contract Value]]-tblReconciliation[[#This Row],[Cost Budget]] -> 470000 | F5: =IFERROR(tblReconciliation[[#This Row],[Planned Margin]]/tblReconciliation[[#This Row],[Contract Value]],0) -> 0.1 | G5: =SUMIFS(tblActualCosts[Amount],tblActualCosts[Project ID],tblReconciliation[Project ID]) -> 459000 | H5: =tblReconciliation[[#This Row],[Cost Budget]]-tblReconciliation[[#This Row],[Actual Spend]] -> 3771000 | I5: =IFERROR(tblReconciliation[[#This Row],[Actual Spend]]/tblReconciliation[[#This Row],[Cost Budget]],0) -> 0.10851064
A6: P005 | B6: =_xll.XLOOKUP(tblReconciliation[[#This Row],[Project ID]],tblProjects[Project ID],tblProjects[Project Name],"Project Not Found") -> Flood Defence Echo | C6: =_xll.XLOOKUP(tblReconciliation[[#This Row],[Project ID]],tblProjects[Project ID],tblProjects[Contract Value],"Budget Not Found") -> 2950000 | D6: =SUMIFS(tblBudget[Budget Amount],tblBudget[Project ID],tblReconciliation[[#This Row],[Project ID]]) -> 2655000 | E6: =tblReconciliation[[#This Row],[Contract Value]]-tblReconciliation[[#This Row],[Cost Budget]] -> 295000 | F6: =IFERROR(tblReconciliation[[#This Row],[Planned Margin]]/tblReconciliation[[#This Row],[Contract Value]],0) -> 0.1 | G6: =SUMIFS(tblActualCosts[Amount],tblActualCosts[Project ID],tblReconciliation[Project ID]) -> 340000 | H6: =tblReconciliation[[#This Row],[Cost Budget]]-tblReconciliation[[#This Row],[Actual Spend]] -> 2315000 | I6: =IFERROR(tblReconciliation[[#This Row],[Actual Spend]]/tblReconciliation[[#This Row],[Cost Budget]],0) -> 0.12806026
A7: Total | C7: =SUBTOTAL(109,tblReconciliation[Contract Value]) -> 22750000 | D7: =SUBTOTAL(109,tblReconciliation[Cost Budget]) -> 20475000 | E7: =SUBTOTAL(109,tblReconciliation[Planned Margin]) -> 2275000 | G7: =SUBTOTAL(109,tblReconciliation[Actual Spend]) -> 3041000 | H7: =SUBTOTAL(109,tblReconciliation[Remaining Budget]) -> 17434000

Sheet Variance_Analysis
A1: Project ID | B1: Project Name | C1: Category ID | D1: Cost Category | E1: Budget | F1: Actual Cost | G1: Remaining Budget | H1: Budget Used % | I1: Variance Status
A2: P001 | B2: =_xll.XLOOKUP(tblVariance[[#This Row],[Project ID]],tblProjects[Project ID],tblProjects[Project Name],"Project not found") -> Bridge Alpha | C2: CAT01 | D2: =_xll.XLOOKUP(tblVariance[[#This Row],[Category ID]],tblCostCategories[Category ID],tblCostCategories[Cost Category],"Category Not Found") -> Labour | E2: =SUMIFS(tblBudget[Budget Amount],tblBudget[Project ID],tblVariance[[#This Row],[Project ID]],tblBudget[Category ID], tblVariance[[#This Row],[Category ID]]) -> 1170000 | F2: =SUMIFS(tblActualCosts[Amount],tblActualCosts[Project ID],tblVariance[[#This Row],[Project ID]],tblActualCosts[Category ID],tblVariance[[#This Row],[Category ID]]) -> 283000 | G2: =tblVariance[[#This Row],[Budget]]-tblVariance[[#This Row],[Actual Cost]] -> 887000 | H2: =IFERROR(tblVariance[[#This Row],[Actual Cost]]/tblVariance[[#This Row],[Budget]],0) -> 0.24188034 | I2: =IF(tblVariance[[#This Row],[Actual Cost]]>tblVariance[[#This Row],[Budget]],"Over Budget",IF(tblVariance[[#This Row],[Budget Used %]]>=0.8,"High Usage",IF(tblVariance[[#This Row],[Budget Used %]]>=0.5,"Monitor","Within Budget"))) -> Within Budget
A3: P001 | B3: =_xll.XLOOKUP(tblVariance[[#This Row],[Project ID]],tblProjects[Project ID],tblProjects[Project Name],"Project not found") -> Bridge Alpha | C3: CAT02 | D3: =_xll.XLOOKUP(tblVariance[[#This Row],[Category ID]],tblCostCategories[Category ID],tblCostCategories[Cost Category],"Category Not Found") -> Materials | E3: =SUMIFS(tblBudget[Budget Amount],tblBudget[Project ID],tblVariance[[#This Row],[Project ID]],tblBudget[Category ID], tblVariance[[#This Row],[Category ID]]) -> 1498000 | F3: =SUMIFS(tblActualCosts[Amount],tblActualCosts[Project ID],tblVariance[[#This Row],[Project ID]],tblActualCosts[Category ID],tblVariance[[#This Row],[Category ID]]) -> 327000 | G3: =tblVariance[[#This Row],[Budget]]-tblVariance[[#This Row],[Actual Cost]] -> 1171000 | H3: =IFERROR(tblVariance[[#This Row],[Actual Cost]]/tblVariance[[#This Row],[Budget]],0) -> 0.21829105 | I3: =IF(tblVariance[[#This Row],[Actual Cost]]>tblVariance[[#This Row],[Budget]],"Over Budget",IF(tblVariance[[#This Row],[Budget Used %]]>=0.8,"High Usage",IF(tblVariance[[#This Row],[Budget Used %]]>=0.5,"Monitor","Within Budget"))) -> Within Budget
A4: P001 | B4: =_xll.XLOOKUP(tblVariance[[#This Row],[Project ID]],tblProjects[Project ID],tblProjects[Project Name],"Project not found") -> Bridge Alpha | C4: CAT03 | D4: =_xll.XLOOKUP(tblVariance[[#This Row],[Category ID]],tblCostCategories[Category ID],tblCostCategories[Cost Category],"Category Not Found") -> Plant Hire | E4: =SUMIFS(tblBudget[Budget Amount],tblBudget[Project ID],tblVariance[[#This Row],[Project ID]],tblBudget[Category ID], tblVariance[[#This Row],[Category ID]]) -> 608000 | F4: =SUMIFS(tblActualCosts[Amount],tblActualCosts[Project ID],tblVariance[[#This Row],[Project ID]],tblActualCosts[Category ID],tblVariance[[#This Row],[Category ID]]) -> 46000 | G4: =tblVariance[[#This Row],[Budget]]-tblVariance[[#This Row],[Actual Cost]] -> 562000 | H4: =IFERROR(tblVariance[[#This Row],[Actual Cost]]/tblVariance[[#This Row],[Budget]],0) -> 0.075657895 | I4: =IF(tblVariance[[#This Row],[Actual Cost]]>tblVariance[[#This Row],[Budget]],"Over Budget",IF(tblVariance[[#This Row],[Budget Used %]]>=0.8,"High Usage",IF(tblVariance[[#This Row],[Budget Used %]]>=0.5,"Monitor","Within Budget"))) -> Within Budget
A5: P001 | B5: =_xll.XLOOKUP(tblVariance[[#This Row],[Project ID]],tblProjects[Project ID],tblProjects[Project Name],"Project not found") -> Bridge Alpha | C5: CAT04 | D5: =_xll.XLOOKUP(tblVariance[[#This Row],[Category ID]],tblCostCategories[Category ID],tblCostCategories[Cost Category],"Category Not Found") -> Subcontractors | E5: =SUMIFS(tblBudget[Budget Amount],tblBudget[Project ID],tblVariance[[#This Row],[Project ID]],tblBudget[Category ID], tblVariance[[#This Row],[Category ID]]) -> 796000 | F5: =SUMIFS(tblActualCosts[Amount],tblActualCosts[Project ID],tblVariance[[#This Row],[Project ID]],tblActualCosts[Category ID],tblVariance[[#This Row],[Category ID]]) -> 125000 | G5: =tblVariance[[#This Row],[Budget]]-tblVariance[[#This Row],[Actual Cost]] -> 671000 | H5: =IFERROR(tblVariance[[#This Row],[Actual Cost]]/tblVariance[[#This Row],[Budget]],0) -> 0.15703518 | I5: =IF(tblVariance[[#This Row],[Actual Cost]]>tblVariance[[#This Row],[Budget]],"Over Budget",IF(tblVariance[[#This Row],[Budget Used %]]>=0.8,"High Usage",IF(tblVariance[[#This Row],[Budget Used %]]>=0.5,"Monitor","Within Budget"))) -> Within Budget
A6: P001 | B6: =_xll.XLOOKUP(tblVariance[[#This Row],[Project ID]],tblProjects[Project ID],tblProjects[Project Name],"Project not found") -> Bridge Alpha | C6: CAT05 | D6: =_xll.XLOOKUP(tblVariance[[#This Row],[Category ID]],tblCostCategories[Category ID],tblCostCategories[Cost Category],"Category Not Found") -> Fuel & Transport | E6: =SUMIFS(tblBudget[Budget Amount],tblBudget[Project ID],tblVariance[[#This Row],[Project ID]],tblBudget[Category ID], tblVariance[[#This Row],[Category ID]]) -> 187000 | F6: =SUMIFS(tblActualCosts[Amount],tblActualCosts[Project ID],tblVariance[[#This Row],[Project ID]],tblActualCosts[Category ID],tblVariance[[#This Row],[Category ID]]) -> 32000 | G6: =tblVariance[[#This Row],[Budget]]-tblVariance[[#This Row],[Actual Cost]] -> 155000 | H6: =IFERROR(tblVariance[[#This Row],[Actual Cost]]/tblVariance[[#This Row],[Budget]],0) -> 0.17112299 | I6: =IF(tblVariance[[#This Row],[Actual Cost]]>tblVariance[[#This Row],[Budget]],"Over Budget",IF(tblVariance[[#This Row],[Budget Used %]]>=0.8,"High Usage",IF(tblVariance[[#This Row],[Budget Used %]]>=0.5,"Monitor","Within Budget"))) -> Within Budget
A7: P001 | B7: =_xll.XLOOKUP(tblVariance[[#This Row],[Project ID]],tblProjects[Project ID],tblProjects[Project Name],"Project not found") -> Bridge Alpha | C7: CAT06 | D7: =_xll.XLOOKUP(tblVariance[[#This Row],[Category ID]],tblCostCategories[Category ID],tblCostCategories[Cost Category],"Category Not Found") -> Site Overheads | E7: =SUMIFS(tblBudget[Budget Amount],tblBudget[Project ID],tblVariance[[#This Row],[Project ID]],tblBudget[Category ID], tblVariance[[#This Row],[Category ID]]) -> 281000 | F7: =SUMIFS(tblActualCosts[Amount],tblActualCosts[Project ID],tblVariance[[#This Row],[Project ID]],tblActualCosts[Category ID],tblVariance[[#This Row],[Category ID]]) -> 48000 | G7: =tblVariance[[#This Row],[Budget]]-tblVariance[[#This Row],[Actual Cost]] -> 233000 | H7: =IFERROR(tblVariance[[#This Row],[Actual Cost]]/tblVariance[[#This Row],[Budget]],0) -> 0.17081851 | I7: =IF(tblVariance[[#This Row],[Actual Cost]]>tblVariance[[#This Row],[Budget]],"Over Budget",IF(tblVariance[[#This Row],[Budget Used %]]>=0.8,"High Usage",IF(tblVariance[[#This Row],[Budget Used %]]>=0.5,"Monitor","Within Budget"))) -> Within Budget
A8: P001 | B8: =_xll.XLOOKUP(tblVariance[[#This Row],[Project ID]],tblProjects[Project ID],tblProjects[Project Name],"Project not found") -> Bridge Alpha | C8: CAT07 | D8: =_xll.XLOOKUP(tblVariance[[#This Row],[Category ID]],tblCostCategories[Category ID],tblCostCategories[Cost Category],"Category Not Found") -> Contingency | E8: =SUMIFS(tblBudget[Budget Amount],tblBudget[Project ID],tblVariance[[#This Row],[Project ID]],tblBudget[Category ID], tblVariance[[#This Row],[Category ID]]) -> 140000 | F8: =SUMIFS(tblActualCosts[Amount],tblActualCosts[Project ID],tblVariance[[#This Row],[Project ID]],tblActualCosts[Category ID],tblVariance[[#This Row],[Category ID]]) -> 0 | G8: =tblVariance[[#This Row],[Budget]]-tblVariance[[#This Row],[Actual Cost]] -> 140000 | H8: =IFERROR(tblVariance[[#This Row],[Actual Cost]]/tblVariance[[#This Row],[Budget]],0) -> 0 | I8: =IF(tblVariance[[#This Row],[Actual Cost]]>tblVariance[[#This Row],[Budget]],"Over Budget",IF(tblVariance[[#This Row],[Budget Used %]]>=0.8,"High Usage",IF(tblVariance[[#This Row],[Budget Used %]]>=0.5,"Monitor","Within Budget"))) -> Within Budget
A9: P002 | B9: =_xll.XLOOKUP(tblVariance[[#This Row],[Project ID]],tblProjects[Project ID],tblProjects[Project Name],"Project not found") -> Water Main Bravo | C9: CAT01 | D9: =_xll.XLOOKUP(tblVariance[[#This Row],[Category ID]],tblCostCategories[Category ID],tblCostCategories[Cost Category],"Category Not Found") -> Labour | E9: =SUMIFS(tblBudget[Budget Amount],tblBudget[Project ID],tblVariance[[#This Row],[Project ID]],tblBudget[Category ID], tblVariance[[#This Row],[Category ID]]) -> 958000 | F9: =SUMIFS(tblActualCosts[Amount],tblActualCosts[Project ID],tblVariance[[#This Row],[Project ID]],tblActualCosts[Category ID],tblVariance[[#This Row],[Category ID]]) -> 163000 | G9: =tblVariance[[#This Row],[Budget]]-tblVariance[[#This Row],[Actual Cost]] -> 795000 | H9: =IFERROR(tblVariance[[#This Row],[Actual Cost]]/tblVariance[[#This Row],[Budget]],0) -> 0.17014614 | I9: =IF(tblVariance[[#This Row],[Actual Cost]]>tblVariance[[#This Row],[Budget]],"Over Budget",IF(tblVariance[[#This Row],[Budget Used %]]>=0.8,"High Usage",IF(tblVariance[[#This Row],[Budget Used %]]>=0.5,"Monitor","Within Budget"))) -> Within Budget
A10: P002 | B10: =_xll.XLOOKUP(tblVariance[[#This Row],[Project ID]],tblProjects[Project ID],tblProjects[Project Name],"Project not found") -> Water Main Bravo | C10: CAT02 | D10: =_xll.XLOOKUP(tblVariance[[#This Row],[Category ID]],tblCostCategories[Category ID],tblCostCategories[Cost Category],"Category Not Found") -> Materials | E10: =SUMIFS(tblBudget[Budget Amount],tblBudget[Project ID],tblVariance[[#This Row],[Project ID]],tblBudget[Category ID], tblVariance[[#This Row],[Category ID]]) -> 923000 | F10: =SUMIFS(tblActualCosts[Amount],tblActualCosts[Project ID],tblVariance[[#This Row],[Project ID]],tblActualCosts[Category ID],tblVariance[[#This Row],[Category ID]]) -> 154000 | G10: =tblVariance[[#This Row],[Budget]]-tblVariance[[#This Row],[Actual Cost]] -> 769000 | H10: =IFERROR(tblVariance[[#This Row],[Actual Cost]]/tblVariance[[#This Row],[Budget]],0) -> 0.16684724 | I10: =IF(tblVariance[[#This Row],[Actual Cost]]>tblVariance[[#This Row],[Budget]],"Over Budget",IF(tblVariance[[#This Row],[Budget Used %]]>=0.8,"High Usage",IF(tblVariance[[#This Row],[Budget Used %]]>=0.5,"Monitor","Within Budget"))) -> Within Budget
A11: P002 | B11: =_xll.XLOOKUP(tblVariance[[#This Row],[Project ID]],tblProjects[Project ID],tblProjects[Project Name],"Project not found") -> Water Main Bravo | C11: CAT03 | D11: =_xll.XLOOKUP(tblVariance[[#This Row],[Category ID]],tblCostCategories[Category ID],tblCostCategories[Cost Category],"Category Not Found") -> Plant Hire | E11: =SUMIFS(tblBudget[Budget Amount],tblBudget[Project ID],tblVariance[[#This Row],[Project ID]],tblBudget[Category ID], tblVariance[[#This Row],[Category ID]]) -> 513000 | F11: =SUMIFS(tblActualCosts[Amount],tblActualCosts[Project ID],tblVariance[[#This Row],[Project ID]],tblActualCosts[Category ID],tblVariance[[#This Row],[Category ID]]) -> 68000 | G11: =tblVariance[[#This Row],[Budget]]-tblVariance[[#This Row],[Actual Cost]] -> 445000 | H11: =IFERROR(tblVariance[[#This Row],[Actual Cost]]/tblVariance[[#This Row],[Budget]],0) -> 0.13255361 | I11: =IF(tblVariance[[#This Row],[Actual Cost]]>tblVariance[[#This Row],[Budget]],"Over Budget",IF(tblVariance[[#This Row],[Budget Used %]]>=0.8,"High Usage",IF(tblVariance[[#This Row],[Budget Used %]]>=0.5,"Monitor","Within Budget"))) -> Within Budget
A12: P002 | B12: =_xll.XLOOKUP(tblVariance[[#This Row],[Project ID]],tblProjects[Project ID],tblProjects[Project Name],"Project not found") -> Water Main Bravo | C12: CAT04 | D12: =_xll.XLOOKUP(tblVariance[[#This Row],[Category ID]],tblCostCategories[Category ID],tblCostCategories[Cost Category],"Category Not Found") -> Subcontractors | E12: =SUMIFS(tblBudget[Budget Amount],tblBudget[Project ID],tblVariance[[#This Row],[Project ID]],tblBudget[Category ID], tblVariance[[#This Row],[Category ID]]) -> 547000 | F12: =SUMIFS(tblActualCosts[Amount],tblActualCosts[Project ID],tblVariance[[#This Row],[Project ID]],tblActualCosts[Category ID],tblVariance[[#This Row],[Category ID]]) -> 92000 | G12: =tblVariance[[#This Row],[Budget]]-tblVariance[[#This Row],[Actual Cost]] -> 455000 | H12: =IFERROR(tblVariance[[#This Row],[Actual Cost]]/tblVariance[[#This Row],[Budget]],0) -> 0.16819013 | I12: =IF(tblVariance[[#This Row],[Actual Cost]]>tblVariance[[#This Row],[Budget]],"Over Budget",IF(tblVariance[[#This Row],[Budget Used %]]>=0.8,"High Usage",IF(tblVariance[[#This Row],[Budget Used %]]>=0.5,"Monitor","Within Budget"))) -> Within Budget
A13: P002 | B13: =_xll.XLOOKUP(tblVariance[[#This Row],[Project ID]],tblProjects[Project ID],tblProjects[Project Name],"Project not found") -> Water Main Bravo | C13: CAT05 | D13: =_xll.XLOOKUP(tblVariance[[#This Row],[Category ID]],tblCostCategories[Category ID],tblCostCategories[Cost Category],"Category Not Found") -> Fuel & Transport | E13: =SUMIFS(tblBudget[Budget Amount],tblBudget[Project ID],tblVariance[[#This Row],[Project ID]],tblBudget[Category ID], tblVariance[[#This Row],[Category ID]]) -> 171000 | F13: =SUMIFS(tblActualCosts[Amount],tblActualCosts[Project ID],tblVariance[[#This Row],[Project ID]],tblActualCosts[Category ID],tblVariance[[#This Row],[Category ID]]) -> 27000 | G13: =tblVariance[[#This Row],[Budget]]-tblVariance[[#This Row],[Actual Cost]] -> 144000 | H13: =IFERROR(tblVariance[[#This Row],[Actual Cost]]/tblVariance[[#This Row],[Budget]],0) -> 0.15789474 | I13: =IF(tblVariance[[#This Row],[Actual Cost]]>tblVariance[[#This Row],[Budget]],"Over Budget",IF(tblVariance[[#This Row],[Budget Used %]]>=0.8,"High Usage",IF(tblVariance[[#This Row],[Budget Used %]]>=0.5,"Monitor","Within Budget"))) -> Within Budget
... A36: P005 | B36: =_xll.XLOOKUP(tblVariance[[#This Row],[Project ID]],tblProjects[Project ID],tblProjects[Project Name],"Project not found") -> Flood Defence Echo | C36: CAT07 | D36: =_xll.XLOOKUP(tblVariance[[#This Row],[Category ID]],tblCostCategories[Category ID],tblCostCategories[Cost Category],"Category Not Found") -> Contingency | E36: =SUMIFS(tblBudget[Budget Amount],tblBudget[Project ID],tblVariance[[#This Row],[Project ID]],tblBudget[Category ID], tblVariance[[#This Row],[Category ID]]) -> 79000 | F36: =SUMIFS(tblActualCosts[Amount],tblActualCosts[Project ID],tblVariance[[#This Row],[Project ID]],tblActualCosts[Category ID],tblVariance[[#This Row],[Category ID]]) -> 0 | G36: =tblVariance[[#This Row],[Budget]]-tblVariance[[#This Row],[Actual Cost]] -> 79000 | H36: =IFERROR(tblVariance[[#This Row],[Actual Cost]]/tblVariance[[#This Row],[Budget]],0) -> 0 | I36: =IF(tblVariance[[#This Row],[Actual Cost]]>tblVariance[[#This Row],[Budget]],"Over Budget",IF(tblVariance[[#This Row],[Budget Used %]]>=0.8,"High Usage",IF(tblVariance[[#This Row],[Budget Used %]]>=0.5,"Monitor","Within Budget"))) -> Within Budget
A37: Total | E37: =SUBTOTAL(109,tblVariance[Budget]) -> 20475000 | F37: =SUBTOTAL(109,tblVariance[Actual Cost]) -> 3041000 | G37: =SUBTOTAL(109,tblVariance[Remaining Budget]) -> 17434000 | H37: =tblVariance[[#Totals],[Actual Cost]]/tblVariance[[#Totals],[Budget]] -> 0.14852259

Sheet Pivot_Analysis
A3: Month | B3: Sum of Amount
A4: 01-Apr | B4: 883000
A5: 01-Mar | B5: 844000
A6: 01-May | B6: 574000
A7: 01-Feb | B7: 411000
A8: 01-Jan | B8: 329000
A9: Grand Total | B9: 3041000
A13: Project Name | B13: (All)
D14: 3041000
A15: Cost Category | B15: Sum of Amount
A16: Materials | B16: 1233000 | C16: 100000 | D16: =C16/$D$14 -> 0.03288392
A17: Labour | B17: 725000 | C17: 725000 | D17: =C17/$D$14 -> 0.23840842
A18: Subcontractors | B18: 543000 | C18: 1233000 | D18: =C18/$D$14 -> 0.40545873
A19: Plant Hire | B19: 392000 | C19: 392000 | D19: =C19/$D$14 -> 0.12890497
A20: Fuel & Transport | B20: 100000 | C20: 48000 | D20: =C20/$D$14 -> 0.015784281
A21: Site Overheads | B21: 48000 | C21: 543000 | D21: =C21/$D$14 -> 0.17855968
A22: Grand Total | B22: 3041000
A24: Project Name | B24: (All)
A26: Supplier | B26: Sum of Amount
A27: Track Materials UK | B27: 172000
A28: Midland Steel Ltd | B28: 185000
A29: Asphalt Direct | B29: 194000
A30: RoadStone Materials | B30: 265000
A31: BuildForce Labour | B31: 283000
A32: Grand Total | B32: 1099000
A39: Row Labels | B39: Count of Project ID
A40: P001 | B40: 1
A41: P002 | B41: 1
A42: P003 | B42: 1
A43: P004 | B43: 1
A44: P005 | B44: 1
A45: Grand Total | B45: 5

Sheet Dashboard
A1: Commercial Cost Dashboard
A3: Reporting Period: January 2026 - May 2026
A6: Total Contract Value | C6: Total Cost Budget | E6: Actual Spend | G6: Remaining Budget | I6: Planned Margin | K6: Budget Used %
A7: =SUM(tblProjects[Contract Value]) -> 22750000 | C7: =SUM(tblBudget[Budget Amount]) -> 20475000 | E7: =SUM(tblActualCosts[Amount]) -> 3041000 | G7: =SUM(tblReconciliation[Remaining Budget]) -> 17434000 | I7: =SUM(tblReconciliation[Planned Margin]) -> 2275000 | K7: =SUM(tblActualCosts[Amount])/SUM(tblBudget[Budget Amount]) -> 0.14852259
A25: Highest Spend Category | C25: Highest Spend Month | E25: Largest Supplier | G25: Project Active
A26: =Pivot_Analysis!A16 -> Materials | C26: =Pivot_Analysis!A5 -> 01-Mar | E26: =Pivot_Analysis!A27 -> Track Materials UK | G26: =GETPIVOTDATA("Project ID",Pivot_Analysis!$A$39) -> 5
A27: =GETPIVOTDATA("Amount",Pivot_Analysis!$A$15,"Cost Category","Materials") -> 1233000 | C27: =GETPIVOTDATA("Amount",Pivot_Analysis!$A$3,"Month",92) -> 883000 | E27: =GETPIVOTDATA("Amount",Pivot_Analysis!$A$26,"Supplier","BuildForce Labour") -> 283000

Sheet Dashboard_data
A1: KPI | B1: Formula
A2: Total Contract Value | B2: =SUM(tblProjects[Contract Value]) -> 22750000
A3: Total Budget | B3: =SUM(tblBudget[Budget Amount]) -> 20475000
A4: Actual Spend | B4: =SUM(tblActualCosts[Amount]) -> 3041000
A5: Remaining Budget | B5: =SUM(tblReconciliation[Remaining Budget]) -> 17434000
A6: Planned Margin | B6: =SUM(tblReconciliation[Planned Margin]) -> 2275000
A7: Budget Used % | B7: =B4/B3 -> 0.14852259
A8: Highest Spend Category | B8: =Pivot_Analysis!A16 -> Materials
A9: Highest Spend Month | B9: =Pivot_Analysis!A5 -> 01-Mar
A10: Largest Supplier | B10: =Pivot_Analysis!A27 -> Track Materials UK
A11: Projects Active | B11: =COUNTA(tblProjects[Project ID]) -> 5
A12: Budget available % | B12: =(B3-B4)/B3 -> 0.85147741
A16: project ID | B16: Project | C16: Budget | D16: Actual | E16: budget used % | F16: Status
A17: P001 | B17: =_xll.XLOOKUP(A17,tblProjects[Project ID],tblProjects[Project Name]) -> Bridge Alpha | C17: =_xll.XLOOKUP(Table9[[#This Row],[project ID]],tblReconciliation[Project ID],tblReconciliation[Cost Budget]) -> 4680000 | D17: =_xll.XLOOKUP(Table9[[#This Row],[project ID]],tblReconciliation[Project ID],tblReconciliation[Actual Spend]) -> 861000 | E17: =_xll.XLOOKUP(Table9[[#This Row],[project ID]],tblReconciliation[Project ID],tblReconciliation[Budget Used %]) -> 0.18397436 | F17: =IFERROR(IF(Table9[[#This Row],[budget used %]]<0.8,"On Track",IF(Table9[[#This Row],[budget used %]]<1,"Monitor","Over Budget")),0) -> On Track
A18: P002 | B18: =_xll.XLOOKUP(A18,tblProjects[Project ID],tblProjects[Project Name]) -> Water Main Bravo | C18: =_xll.XLOOKUP(Table9[[#This Row],[project ID]],tblReconciliation[Project ID],tblReconciliation[Cost Budget]) -> 3420000 | D18: =_xll.XLOOKUP(Table9[[#This Row],[project ID]],tblReconciliation[Project ID],tblReconciliation[Actual Spend]) -> 504000 | E18: =_xll.XLOOKUP(Table9[[#This Row],[project ID]],tblReconciliation[Project ID],tblReconciliation[Budget Used %]) -> 0.14736842 | F18: =IFERROR(IF(Table9[[#This Row],[budget used %]]<0.8,"On Track",IF(Table9[[#This Row],[budget used %]]<1,"Monitor","Over Budget")),0) -> On Track
A19: P003 | B19: =_xll.XLOOKUP(A19,tblProjects[Project ID],tblProjects[Project Name]) -> Highway Charlie | C19: =_xll.XLOOKUP(Table9[[#This Row],[project ID]],tblReconciliation[Project ID],tblReconciliation[Cost Budget]) -> 5490000 | D19: =_xll.XLOOKUP(Table9[[#This Row],[project ID]],tblReconciliation[Project ID],tblReconciliation[Actual Spend]) -> 877000 | E19: =_xll.XLOOKUP(Table9[[#This Row],[project ID]],tblReconciliation[Project ID],tblReconciliation[Budget Used %]) -> 0.15974499 | F19: =IFERROR(IF(Table9[[#This Row],[budget used %]]<0.8,"On Track",IF(Table9[[#This Row],[budget used %]]<1,"Monitor","Over Budget")),0) -> On Track
A20: P004 | B20: =_xll.XLOOKUP(A20,tblProjects[Project ID],tblProjects[Project Name]) -> Rail Extension Delta | C20: =_xll.XLOOKUP(Table9[[#This Row],[project ID]],tblReconciliation[Project ID],tblReconciliation[Cost Budget]) -> 4230000 | D20: =_xll.XLOOKUP(Table9[[#This Row],[project ID]],tblReconciliation[Project ID],tblReconciliation[Actual Spend]) -> 459000 | E20: =_xll.XLOOKUP(Table9[[#This Row],[project ID]],tblReconciliation[Project ID],tblReconciliation[Budget Used %]) -> 0.10851064 | F20: =IFERROR(IF(Table9[[#This Row],[budget used %]]<0.8,"On Track",IF(Table9[[#This Row],[budget used %]]<1,"Monitor","Over Budget")),0) -> On Track
A21: P005 | B21: =_xll.XLOOKUP(A21,tblProjects[Project ID],tblProjects[Project Name]) -> Flood Defence Echo | C21: =_xll.XLOOKUP(Table9[[#This Row],[project ID]],tblReconciliation[Project ID],tblReconciliation[Cost Budget]) -> 2655000 | D21: =_xll.XLOOKUP(Table9[[#This Row],[project ID]],tblReconciliation[Project ID],tblReconciliation[Actual Spend]) -> 340000 | E21: =_xll.XLOOKUP(Table9[[#This Row],[project ID]],tblReconciliation[Project ID],tblReconciliation[Budget Used %]) -> 0.12806026 | F21: =IFERROR(IF(Table9[[#This Row],[budget used %]]<0.8,"On Track",IF(Table9[[#This Row],[budget used %]]<1,"Monitor","Over Budget")),0) -> On Track
A26: Project | B26: Status | C26: Budget used | D26: Manager
A27: Bridge Alpha | B27: =IF(Table10[[#This Row],[Budget used]]<0.8,"On Track",IF(Table10[[#This Row],[Budget used]]<1,"Monitor","Over Budget")) -> On Track | C27: =D17/C17 -> 0.18397436 | D27: James Carter
A28: Water Main Bravo | B28: =IF(Table10[[#This Row],[Budget used]]<0.8,"On Track",IF(Table10[[#This Row],[Budget used]]<1,"Monitor","Over Budget")) -> On Track | C28: =D18/C18 -> 0.14736842 | D28: Sarah Ahmed
A29: Highway Charlie | B29: =IF(Table10[[#This Row],[Budget used]]<0.8,"On Track",IF(Table10[[#This Row],[Budget used]]<1,"Monitor","Over Budget")) -> On Track | C29: =D19/C19 -> 0.15974499 | D29: Michael Green
A30: Rail Extension Delta | B30: =IF(Table10[[#This Row],[Budget used]]<0.8,"On Track",IF(Table10[[#This Row],[Budget used]]<1,"Monitor","Over Budget")) -> On Track | C30: =D20/C20 -> 0.10851064 | D30: Emma Lewis
A31: Flood Defence Echo | B31: =IF(Table10[[#This Row],[Budget used]]<0.8,"On Track",IF(Table10[[#This Row],[Budget used]]<1,"Monitor","Over Budget")) -> On Track | C31: =D21/C21 -> 0.12806026 | D31: Daniel Hughes
H42: dd

Sheet Dashboard II
B2: Joseph Gallagher Group Commercial Cost Dashboard
B5: Reporting Period: January 2026 - May 2026
B44: Project | C44: Status | D44: Budget Used % | E44: Manager
B45: =Dashboard_data!A27 -> Bridge Alpha | C45: =Dashboard_data!B27 -> On Track | D45: =Dashboard_data!C27 -> 0.18397436 | E45: =Dashboard_data!D27 -> James Carter
B46: =Dashboard_data!A28 -> Water Main Bravo | C46: =Dashboard_data!B28 -> On Track | D46: =Dashboard_data!C28 -> 0.14736842 | E46: =Dashboard_data!D28 -> Sarah Ahmed
B47: =Dashboard_data!A29 -> Highway Charlie | C47: =Dashboard_data!B29 -> On Track | D47: =Dashboard_data!C29 -> 0.15974499 | E47: =Dashboard_data!D29 -> Michael Green
B48: =Dashboard_data!A30 -> Rail Extension Delta | C48: =Dashboard_data!B30 -> On Track | D48: =Dashboard_data!C30 -> 0.10851064 | E48: =Dashboard_data!D30 -> Emma Lewis
B49: =Dashboard_data!A31 -> Flood Defence Echo | C49: =Dashboard_data!B31 -> On Track | D49: =Dashboard_data!C31 -> 0.12806026 | E49: =Dashboard_data!D31 -> Daniel Hughes
